ddir/__init__.py
ddir/__main__.py
ddir/__version__.py
ddir/diff.py
ddir/initialize.py
ddir/legacy.py
ddir/target.py
ddir-3.1.2.dist-info/LICENSE
ddir-3.1.2.dist-info/METADATA
ddir-3.1.2.dist-info/WHEEL
ddir-3.1.2.dist-info/entry_points.txt
ddir-3.1.2.dist-info/top_level.txt
ddir-3.1.2.dist-info/RECORD
