Metadata-Version: 2.1
Name: ddir
Version: 3.1.2
Summary: Diff a directory and sync changes.
License: Public Domain
License-File: LICENSE
